[
  {
    "id": "j001",
    "numero": 1,
    "fase": "Fase de grupos",
    "grupo": "Grupo A",
    "data": "2026-06-11",
    "horario": "16:00",
    "selecaoA": "México",
    "selecaoB": "África do Sul",
    "estadio": "Estádio da Cidade do México",
    "cidade": "Cidade do México",
    "status": "Aguardando jogo",
    "placarA": null,
    "placarB": null
  },
  {
    "id": "j002",
    "numero": 2,
    "fase": "Fase de grupos",
    "grupo": "Grupo A",
    "data": "2026-06-11",
    "horario": "23:00",
    "selecaoA": "República da Coreia",
    "selecaoB": "Tchéquia",
    "estadio": "Estádio de Guadalajara",
    "cidade": "Guadalajara",
    "status": "Aguardando jogo",
    "placarA": null,
    "placarB": null
  },
  {
    "id": "j003",
    "numero": 3,
    "fase": "Fase de grupos",
    "grupo": "Grupo B",
    "data": "2026-06-12",
    "horario": "16:00",
    "selecaoA": "Canadá",
    "selecaoB": "Bósnia e Herzegovina",
    "estadio": "Estádio de Toronto",
    "cidade": "Toronto",
    "status": "Aguardando jogo",
    "placarA": null,
    "placarB": null
  },
  {
    "id": "j004",
    "numero": 4,
    "fase": "Fase de grupos",
    "grupo": "Grupo D",
    "data": "2026-06-12",
    "horario": "22:00",
    "selecaoA": "Estados Unidos",
    "selecaoB": "Paraguai",
    "estadio": "Estádio de Los Angeles",
    "cidade": "Los Angeles",
    "status": "Aguardando jogo",
    "placarA": null,
    "placarB": null
  },
  {
    "id": "j005",
    "numero": 5,
    "fase": "Fase de grupos",
    "grupo": "Grupo C",
    "data": "2026-06-13",
    "horario": "22:00",
    "selecaoA": "Haiti",
    "selecaoB": "Escócia",
    "estadio": "Estádio de Boston",
    "cidade": "Boston",
    "status": "Aguardando jogo",
    "placarA": null,
    "placarB": null
  },
  {
    "id": "j006",
    "numero": 6,
    "fase": "Fase de grupos",
    "grupo": "Grupo D",
    "data": "2026-06-13",
    "horario": "01:00",
    "selecaoA": "Austrália",
    "selecaoB": "Turquia",
    "estadio": "BC Place",
    "cidade": "Vancouver",
    "status": "Aguardando jogo",
    "placarA": null,
    "placarB": null
  },
  {
    "id": "j007",
    "numero": 7,
    "fase": "Fase de grupos",
    "grupo": "Grupo C",
    "data": "2026-06-13",
    "horario": "19:00",
    "selecaoA": "Brasil",
    "selecaoB": "Marrocos",
    "estadio": "Estádio de Nova York/Nova Jersey",
    "cidade": "Nova York/Nova Jersey",
    "status": "Aguardando jogo",
    "placarA": null,
    "placarB": null
  },
  {
    "id": "j008",
    "numero": 8,
    "fase": "Fase de grupos",
    "grupo": "Grupo B",
    "data": "2026-06-13",
    "horario": "16:00",
    "selecaoA": "Catar",
    "selecaoB": "Suíça",
    "estadio": "Estádio da Baía de São Francisco",
    "cidade": "São Francisco",
    "status": "Aguardando jogo",
    "placarA": null,
    "placarB": null
  },
  {
    "id": "j009",
    "numero": 9,
    "fase": "Fase de grupos",
    "grupo": "Grupo E",
    "data": "2026-06-14",
    "horario": "20:00",
    "selecaoA": "Costa do Marfim",
    "selecaoB": "Equador",
    "estadio": "Estádio da Filadélfia",
    "cidade": "Filadélfia",
    "status": "Aguardando jogo",
    "placarA": null,
    "placarB": null
  },
  {
    "id": "j010",
    "numero": 10,
    "fase": "Fase de grupos",
    "grupo": "Grupo E",
    "data": "2026-06-14",
    "horario": "14:00",
    "selecaoA": "Alemanha",
    "selecaoB": "Curaçao",
    "estadio": "Estádio de Houston",
    "cidade": "Houston",
    "status": "Aguardando jogo",
    "placarA": null,
    "placarB": null
  },
  {
    "id": "j011",
    "numero": 11,
    "fase": "Fase de grupos",
    "grupo": "Grupo F",
    "data": "2026-06-14",
    "horario": "17:00",
    "selecaoA": "Países Baixos",
    "selecaoB": "Japão",
    "estadio": "Estádio de Dallas",
    "cidade": "Dallas",
    "status": "Aguardando jogo",
    "placarA": null,
    "placarB": null
  },
  {
    "id": "j012",
    "numero": 12,
    "fase": "Fase de grupos",
    "grupo": "Grupo F",
    "data": "2026-06-14",
    "horario": "23:00",
    "selecaoA": "Suécia",
    "selecaoB": "Tunísia",
    "estadio": "Estádio de Monterrey",
    "cidade": "Monterrey",
    "status": "Aguardando jogo",
    "placarA": null,
    "placarB": null
  },
  {
    "id": "j013",
    "numero": 13,
    "fase": "Fase de grupos",
    "grupo": "Grupo H",
    "data": "2026-06-15",
    "horario": "19:00",
    "selecaoA": "Arábia Saudita",
    "selecaoB": "Uruguai",
    "estadio": "Estádio de Miami",
    "cidade": "Miami",
    "status": "Aguardando jogo",
    "placarA": null,
    "placarB": null
  },
  {
    "id": "j014",
    "numero": 14,
    "fase": "Fase de grupos",
    "grupo": "Grupo H",
    "data": "2026-06-15",
    "horario": "13:00",
    "selecaoA": "Espanha",
    "selecaoB": "Cabo Verde",
    "estadio": "Estádio de Atlanta",
    "cidade": "Atlanta",
    "status": "Aguardando jogo",
    "placarA": null,
    "placarB": null
  },
  {
    "id": "j015",
    "numero": 15,
    "fase": "Fase de grupos",
    "grupo": "Grupo G",
    "data": "2026-06-15",
    "horario": "22:00",
    "selecaoA": "Irã",
    "selecaoB": "Nova Zelândia",
    "estadio": "Estádio de Los Angeles",
    "cidade": "Los Angeles",
    "status": "Aguardando jogo",
    "placarA": null,
    "placarB": null
  },
  {
    "id": "j016",
    "numero": 16,
    "fase": "Fase de grupos",
    "grupo": "Grupo G",
    "data": "2026-06-15",
    "horario": "16:00",
    "selecaoA": "Bélgica",
    "selecaoB": "Egito",
    "estadio": "Estádio de Seattle",
    "cidade": "Seattle",
    "status": "Aguardando jogo",
    "placarA": null,
    "placarB": null
  },
  {
    "id": "j017",
    "numero": 17,
    "fase": "Fase de grupos",
    "grupo": "Grupo I",
    "data": "2026-06-16",
    "horario": "16:00",
    "selecaoA": "França",
    "selecaoB": "Senegal",
    "estadio": "Estádio de Nova York/Nova Jersey",
    "cidade": "Nova York/Nova Jersey",
    "status": "Aguardando jogo",
    "placarA": null,
    "placarB": null
  },
  {
    "id": "j018",
    "numero": 18,
    "fase": "Fase de grupos",
    "grupo": "Grupo I",
    "data": "2026-06-16",
    "horario": "19:00",
    "selecaoA": "Iraque",
    "selecaoB": "Noruega",
    "estadio": "Estádio de Boston",
    "cidade": "Boston",
    "status": "Aguardando jogo",
    "placarA": null,
    "placarB": null
  },
  {
    "id": "j019",
    "numero": 19,
    "fase": "Fase de grupos",
    "grupo": "Grupo J",
    "data": "2026-06-16",
    "horario": "22:00",
    "selecaoA": "Argentina",
    "selecaoB": "Argélia",
    "estadio": "Estádio de Kansas City",
    "cidade": "Kansas City",
    "status": "Aguardando jogo",
    "placarA": null,
    "placarB": null
  },
  {
    "id": "j020",
    "numero": 20,
    "fase": "Fase de grupos",
    "grupo": "Grupo J",
    "data": "2026-06-16",
    "horario": "01:00",
    "selecaoA": "Áustria",
    "selecaoB": "Jordânia",
    "estadio": "Estádio da Baía de São Francisco",
    "cidade": "São Francisco",
    "status": "Aguardando jogo",
    "placarA": null,
    "placarB": null
  },
  {
    "id": "j021",
    "numero": 21,
    "fase": "Fase de grupos",
    "grupo": "Grupo L",
    "data": "2026-06-17",
    "horario": "20:00",
    "selecaoA": "Gana",
    "selecaoB": "Panamá",
    "estadio": "Estádio de Toronto",
    "cidade": "Toronto",
    "status": "Aguardando jogo",
    "placarA": null,
    "placarB": null
  },
  {
    "id": "j022",
    "numero": 22,
    "fase": "Fase de grupos",
    "grupo": "Grupo L",
    "data": "2026-06-17",
    "horario": "17:00",
    "selecaoA": "Inglaterra",
    "selecaoB": "Croácia",
    "estadio": "Estádio de Dallas",
    "cidade": "Dallas",
    "status": "Aguardando jogo",
    "placarA": null,
    "placarB": null
  },
  {
    "id": "j023",
    "numero": 23,
    "fase": "Fase de grupos",
    "grupo": "Grupo K",
    "data": "2026-06-17",
    "horario": "14:00",
    "selecaoA": "Portugal",
    "selecaoB": "RD Congo",
    "estadio": "Estádio de Houston",
    "cidade": "Houston",
    "status": "Aguardando jogo",
    "placarA": null,
    "placarB": null
  },
  {
    "id": "j024",
    "numero": 24,
    "fase": "Fase de grupos",
    "grupo": "Grupo K",
    "data": "2026-06-17",
    "horario": "23:00",
    "selecaoA": "Uzbequistão",
    "selecaoB": "Colômbia",
    "estadio": "Estádio da Cidade do México",
    "cidade": "Cidade do México",
    "status": "Aguardando jogo",
    "placarA": null,
    "placarB": null
  },
  {
    "id": "j025",
    "numero": 25,
    "fase": "Fase de grupos",
    "grupo": "Grupo A",
    "data": "2026-06-18",
    "horario": "13:00",
    "selecaoA": "Tchéquia",
    "selecaoB": "África do Sul",
    "estadio": "Estádio de Atlanta",
    "cidade": "Atlanta",
    "status": "Aguardando jogo",
    "placarA": null,
    "placarB": null
  },
  {
    "id": "j026",
    "numero": 26,
    "fase": "Fase de grupos",
    "grupo": "Grupo B",
    "data": "2026-06-18",
    "horario": "16:00",
    "selecaoA": "Suíça",
    "selecaoB": "Bósnia e Herzegovina",
    "estadio": "Estádio de Los Angeles",
    "cidade": "Los Angeles",
    "status": "Aguardando jogo",
    "placarA": null,
    "placarB": null
  },
  {
    "id": "j027",
    "numero": 27,
    "fase": "Fase de grupos",
    "grupo": "Grupo B",
    "data": "2026-06-18",
    "horario": "19:00",
    "selecaoA": "Canadá",
    "selecaoB": "Catar",
    "estadio": "BC Place",
    "cidade": "Vancouver",
    "status": "Aguardando jogo",
    "placarA": null,
    "placarB": null
  },
  {
    "id": "j028",
    "numero": 28,
    "fase": "Fase de grupos",
    "grupo": "Grupo A",
    "data": "2026-06-18",
    "horario": "22:00",
    "selecaoA": "México",
    "selecaoB": "República da Coreia",
    "estadio": "Estádio de Guadalajara",
    "cidade": "Guadalajara",
    "status": "Aguardando jogo",
    "placarA": null,
    "placarB": null
  },
  {
    "id": "j029",
    "numero": 29,
    "fase": "Fase de grupos",
    "grupo": "Grupo C",
    "data": "2026-06-19",
    "horario": "22:00",
    "selecaoA": "Brasil",
    "selecaoB": "Haiti",
    "estadio": "Estádio da Filadélfia",
    "cidade": "Filadélfia",
    "status": "Aguardando jogo",
    "placarA": null,
    "placarB": null
  },
  {
    "id": "j030",
    "numero": 30,
    "fase": "Fase de grupos",
    "grupo": "Grupo C",
    "data": "2026-06-19",
    "horario": "19:00",
    "selecaoA": "Escócia",
    "selecaoB": "Marrocos",
    "estadio": "Estádio de Boston",
    "cidade": "Boston",
    "status": "Aguardando jogo",
    "placarA": null,
    "placarB": null
  },
  {
    "id": "j031",
    "numero": 31,
    "fase": "Fase de grupos",
    "grupo": "Grupo D",
    "data": "2026-06-20",
    "horario": "00:00",
    "selecaoA": "Turquia",
    "selecaoB": "Paraguai",
    "estadio": "Estádio da Baía de São Francisco",
    "cidade": "São Francisco",
    "status": "Aguardando jogo",
    "placarA": null,
    "placarB": null
  },
  {
    "id": "j032",
    "numero": 32,
    "fase": "Fase de grupos",
    "grupo": "Grupo D",
    "data": "2026-06-19",
    "horario": "16:00",
    "selecaoA": "Estados Unidos",
    "selecaoB": "Austrália",
    "estadio": "Estádio de Seattle",
    "cidade": "Seattle",
    "status": "Aguardando jogo",
    "placarA": null,
    "placarB": null
  },
  {
    "id": "j033",
    "numero": 33,
    "fase": "Fase de grupos",
    "grupo": "Grupo E",
    "data": "2026-06-20",
    "horario": "17:00",
    "selecaoA": "Alemanha",
    "selecaoB": "Costa do Marfim",
    "estadio": "Estádio de Toronto",
    "cidade": "Toronto",
    "status": "Aguardando jogo",
    "placarA": null,
    "placarB": null
  },
  {
    "id": "j034",
    "numero": 34,
    "fase": "Fase de grupos",
    "grupo": "Grupo E",
    "data": "2026-06-20",
    "horario": "21:00",
    "selecaoA": "Equador",
    "selecaoB": "Curaçao",
    "estadio": "Estádio de Kansas City",
    "cidade": "Kansas City",
    "status": "Aguardando jogo",
    "placarA": null,
    "placarB": null
  },
  {
    "id": "j035",
    "numero": 35,
    "fase": "Fase de grupos",
    "grupo": "Grupo F",
    "data": "2026-06-20",
    "horario": "14:00",
    "selecaoA": "Países Baixos",
    "selecaoB": "Suécia",
    "estadio": "Estádio de Houston",
    "cidade": "Houston",
    "status": "Aguardando jogo",
    "placarA": null,
    "placarB": null
  },
  {
    "id": "j036",
    "numero": 36,
    "fase": "Fase de grupos",
    "grupo": "Grupo F",
    "data": "2026-06-20",
    "horario": "01:00",
    "selecaoA": "Tunísia",
    "selecaoB": "Japão",
    "estadio": "Estádio de Monterrey",
    "cidade": "Monterrey",
    "status": "Aguardando jogo",
    "placarA": null,
    "placarB": null
  },
  {
    "id": "j037",
    "numero": 37,
    "fase": "Fase de grupos",
    "grupo": "Grupo H",
    "data": "2026-06-21",
    "horario": "19:00",
    "selecaoA": "Uruguai",
    "selecaoB": "Cabo Verde",
    "estadio": "Estádio de Miami",
    "cidade": "Miami",
    "status": "Aguardando jogo",
    "placarA": null,
    "placarB": null
  },
  {
    "id": "j038",
    "numero": 38,
    "fase": "Fase de grupos",
    "grupo": "Grupo H",
    "data": "2026-06-21",
    "horario": "13:00",
    "selecaoA": "Espanha",
    "selecaoB": "Arábia Saudita",
    "estadio": "Estádio de Atlanta",
    "cidade": "Atlanta",
    "status": "Aguardando jogo",
    "placarA": null,
    "placarB": null
  },
  {
    "id": "j039",
    "numero": 39,
    "fase": "Fase de grupos",
    "grupo": "Grupo G",
    "data": "2026-06-21",
    "horario": "16:00",
    "selecaoA": "Bélgica",
    "selecaoB": "Irã",
    "estadio": "Estádio de Los Angeles",
    "cidade": "Los Angeles",
    "status": "Aguardando jogo",
    "placarA": null,
    "placarB": null
  },
  {
    "id": "j040",
    "numero": 40,
    "fase": "Fase de grupos",
    "grupo": "Grupo G",
    "data": "2026-06-21",
    "horario": "22:00",
    "selecaoA": "Nova Zelândia",
    "selecaoB": "Egito",
    "estadio": "BC Place",
    "cidade": "Vancouver",
    "status": "Aguardando jogo",
    "placarA": null,
    "placarB": null
  },
  {
    "id": "j041",
    "numero": 41,
    "fase": "Fase de grupos",
    "grupo": "Grupo I",
    "data": "2026-06-22",
    "horario": "21:00",
    "selecaoA": "Noruega",
    "selecaoB": "Senegal",
    "estadio": "Estádio de Nova York/Nova Jersey",
    "cidade": "Nova York/Nova Jersey",
    "status": "Aguardando jogo",
    "placarA": null,
    "placarB": null
  },
  {
    "id": "j042",
    "numero": 42,
    "fase": "Fase de grupos",
    "grupo": "Grupo I",
    "data": "2026-06-22",
    "horario": "18:00",
    "selecaoA": "França",
    "selecaoB": "Iraque",
    "estadio": "Estádio da Filadélfia",
    "cidade": "Filadélfia",
    "status": "Aguardando jogo",
    "placarA": null,
    "placarB": null
  },
  {
    "id": "j043",
    "numero": 43,
    "fase": "Fase de grupos",
    "grupo": "Grupo J",
    "data": "2026-06-22",
    "horario": "14:00",
    "selecaoA": "Argentina",
    "selecaoB": "Áustria",
    "estadio": "Estádio de Dallas",
    "cidade": "Dallas",
    "status": "Aguardando jogo",
    "placarA": null,
    "placarB": null
  },
  {
    "id": "j044",
    "numero": 44,
    "fase": "Fase de grupos",
    "grupo": "Grupo J",
    "data": "2026-06-23",
    "horario": "00:00",
    "selecaoA": "Jordânia",
    "selecaoB": "Argélia",
    "estadio": "Estádio da Baía de São Francisco",
    "cidade": "São Francisco",
    "status": "Aguardando jogo",
    "placarA": null,
    "placarB": null
  },
  {
    "id": "j045",
    "numero": 45,
    "fase": "Fase de grupos",
    "grupo": "Grupo L",
    "data": "2026-06-23",
    "horario": "17:00",
    "selecaoA": "Inglaterra",
    "selecaoB": "Gana",
    "estadio": "Estádio de Boston",
    "cidade": "Boston",
    "status": "Aguardando jogo",
    "placarA": null,
    "placarB": null
  },
  {
    "id": "j046",
    "numero": 46,
    "fase": "Fase de grupos",
    "grupo": "Grupo L",
    "data": "2026-06-23",
    "horario": "20:00",
    "selecaoA": "Panamá",
    "selecaoB": "Croácia",
    "estadio": "Estádio de Toronto",
    "cidade": "Toronto",
    "status": "Aguardando jogo",
    "placarA": null,
    "placarB": null
  },
  {
    "id": "j047",
    "numero": 47,
    "fase": "Fase de grupos",
    "grupo": "Grupo K",
    "data": "2026-06-23",
    "horario": "14:00",
    "selecaoA": "Portugal",
    "selecaoB": "Uzbequistão",
    "estadio": "Estádio de Houston",
    "cidade": "Houston",
    "status": "Aguardando jogo",
    "placarA": null,
    "placarB": null
  },
  {
    "id": "j048",
    "numero": 48,
    "fase": "Fase de grupos",
    "grupo": "Grupo K",
    "data": "2026-06-23",
    "horario": "23:00",
    "selecaoA": "Colômbia",
    "selecaoB": "RD Congo",
    "estadio": "Estádio de Guadalajara",
    "cidade": "Guadalajara",
    "status": "Aguardando jogo",
    "placarA": null,
    "placarB": null
  },
  {
    "id": "j049",
    "numero": 49,
    "fase": "Fase de grupos",
    "grupo": "Grupo C",
    "data": "2026-06-24",
    "horario": "19:00",
    "selecaoA": "Escócia",
    "selecaoB": "Brasil",
    "estadio": "Estádio de Miami",
    "cidade": "Miami",
    "status": "Aguardando jogo",
    "placarA": null,
    "placarB": null
  },
  {
    "id": "j050",
    "numero": 50,
    "fase": "Fase de grupos",
    "grupo": "Grupo C",
    "data": "2026-06-24",
    "horario": "19:00",
    "selecaoA": "Marrocos",
    "selecaoB": "Haiti",
    "estadio": "Estádio de Atlanta",
    "cidade": "Atlanta",
    "status": "Aguardando jogo",
    "placarA": null,
    "placarB": null
  },
  {
    "id": "j051",
    "numero": 51,
    "fase": "Fase de grupos",
    "grupo": "Grupo B",
    "data": "2026-06-24",
    "horario": "16:00",
    "selecaoA": "Suíça",
    "selecaoB": "Canadá",
    "estadio": "BC Place",
    "cidade": "Vancouver",
    "status": "Aguardando jogo",
    "placarA": null,
    "placarB": null
  },
  {
    "id": "j052",
    "numero": 52,
    "fase": "Fase de grupos",
    "grupo": "Grupo B",
    "data": "2026-06-24",
    "horario": "16:00",
    "selecaoA": "Bósnia e Herzegovina",
    "selecaoB": "Catar",
    "estadio": "Estádio de Seattle",
    "cidade": "Seattle",
    "status": "Aguardando jogo",
    "placarA": null,
    "placarB": null
  },
  {
    "id": "j053",
    "numero": 53,
    "fase": "Fase de grupos",
    "grupo": "Grupo A",
    "data": "2026-06-24",
    "horario": "22:00",
    "selecaoA": "Tchéquia",
    "selecaoB": "México",
    "estadio": "Estádio da Cidade do México",
    "cidade": "Cidade do México",
    "status": "Aguardando jogo",
    "placarA": null,
    "placarB": null
  },
  {
    "id": "j054",
    "numero": 54,
    "fase": "Fase de grupos",
    "grupo": "Grupo A",
    "data": "2026-06-24",
    "horario": "22:00",
    "selecaoA": "África do Sul",
    "selecaoB": "República da Coreia",
    "estadio": "Estádio de Monterrey",
    "cidade": "Monterrey",
    "status": "Aguardando jogo",
    "placarA": null,
    "placarB": null
  },
  {
    "id": "j055",
    "numero": 55,
    "fase": "Fase de grupos",
    "grupo": "Grupo E",
    "data": "2026-06-25",
    "horario": "17:00",
    "selecaoA": "Curaçao",
    "selecaoB": "Costa do Marfim",
    "estadio": "Estádio da Filadélfia",
    "cidade": "Filadélfia",
    "status": "Aguardando jogo",
    "placarA": null,
    "placarB": null
  },
  {
    "id": "j056",
    "numero": 56,
    "fase": "Fase de grupos",
    "grupo": "Grupo E",
    "data": "2026-06-25",
    "horario": "17:00",
    "selecaoA": "Equador",
    "selecaoB": "Alemanha",
    "estadio": "Estádio de Nova York/Nova Jersey",
    "cidade": "Nova York/Nova Jersey",
    "status": "Aguardando jogo",
    "placarA": null,
    "placarB": null
  },
  {
    "id": "j057",
    "numero": 57,
    "fase": "Fase de grupos",
    "grupo": "Grupo F",
    "data": "2026-06-25",
    "horario": "20:00",
    "selecaoA": "Japão",
    "selecaoB": "Suécia",
    "estadio": "Estádio de Dallas",
    "cidade": "Dallas",
    "status": "Aguardando jogo",
    "placarA": null,
    "placarB": null
  },
  {
    "id": "j058",
    "numero": 58,
    "fase": "Fase de grupos",
    "grupo": "Grupo F",
    "data": "2026-06-25",
    "horario": "20:00",
    "selecaoA": "Tunísia",
    "selecaoB": "Países Baixos",
    "estadio": "Estádio de Kansas City",
    "cidade": "Kansas City",
    "status": "Aguardando jogo",
    "placarA": null,
    "placarB": null
  },
  {
    "id": "j059",
    "numero": 59,
    "fase": "Fase de grupos",
    "grupo": "Grupo D",
    "data": "2026-06-25",
    "horario": "23:00",
    "selecaoA": "Turquia",
    "selecaoB": "Estados Unidos",
    "estadio": "Estádio de Los Angeles",
    "cidade": "Los Angeles",
    "status": "Aguardando jogo",
    "placarA": null,
    "placarB": null
  },
  {
    "id": "j060",
    "numero": 60,
    "fase": "Fase de grupos",
    "grupo": "Grupo D",
    "data": "2026-06-25",
    "horario": "23:00",
    "selecaoA": "Paraguai",
    "selecaoB": "Austrália",
    "estadio": "Estádio da Baía de São Francisco",
    "cidade": "São Francisco",
    "status": "Aguardando jogo",
    "placarA": null,
    "placarB": null
  },
  {
    "id": "j061",
    "numero": 61,
    "fase": "Fase de grupos",
    "grupo": "Grupo I",
    "data": "2026-06-26",
    "horario": "16:00",
    "selecaoA": "Noruega",
    "selecaoB": "França",
    "estadio": "Estádio de Boston",
    "cidade": "Boston",
    "status": "Aguardando jogo",
    "placarA": null,
    "placarB": null
  },
  {
    "id": "j062",
    "numero": 62,
    "fase": "Fase de grupos",
    "grupo": "Grupo I",
    "data": "2026-06-26",
    "horario": "16:00",
    "selecaoA": "Senegal",
    "selecaoB": "Iraque",
    "estadio": "Estádio de Toronto",
    "cidade": "Toronto",
    "status": "Aguardando jogo",
    "placarA": null,
    "placarB": null
  },
  {
    "id": "j063",
    "numero": 63,
    "fase": "Fase de grupos",
    "grupo": "Grupo G",
    "data": "2026-06-27",
    "horario": "00:00",
    "selecaoA": "Egito",
    "selecaoB": "Irã",
    "estadio": "Estádio de Seattle",
    "cidade": "Seattle",
    "status": "Aguardando jogo",
    "placarA": null,
    "placarB": null
  },
  {
    "id": "j064",
    "numero": 64,
    "fase": "Fase de grupos",
    "grupo": "Grupo G",
    "data": "2026-06-27",
    "horario": "00:00",
    "selecaoA": "Nova Zelândia",
    "selecaoB": "Bélgica",
    "estadio": "BC Place",
    "cidade": "Vancouver",
    "status": "Aguardando jogo",
    "placarA": null,
    "placarB": null
  },
  {
    "id": "j065",
    "numero": 65,
    "fase": "Fase de grupos",
    "grupo": "Grupo H",
    "data": "2026-06-26",
    "horario": "21:00",
    "selecaoA": "Cabo Verde",
    "selecaoB": "Arábia Saudita",
    "estadio": "Estádio de Houston",
    "cidade": "Houston",
    "status": "Aguardando jogo",
    "placarA": null,
    "placarB": null
  },
  {
    "id": "j066",
    "numero": 66,
    "fase": "Fase de grupos",
    "grupo": "Grupo H",
    "data": "2026-06-26",
    "horario": "21:00",
    "selecaoA": "Uruguai",
    "selecaoB": "Espanha",
    "estadio": "Estádio de Guadalajara",
    "cidade": "Guadalajara",
    "status": "Aguardando jogo",
    "placarA": null,
    "placarB": null
  },
  {
    "id": "j067",
    "numero": 67,
    "fase": "Fase de grupos",
    "grupo": "Grupo L",
    "data": "2026-06-27",
    "horario": "18:00",
    "selecaoA": "Panamá",
    "selecaoB": "Inglaterra",
    "estadio": "Estádio de Nova York/Nova Jersey",
    "cidade": "Nova York/Nova Jersey",
    "status": "Aguardando jogo",
    "placarA": null,
    "placarB": null
  },
  {
    "id": "j068",
    "numero": 68,
    "fase": "Fase de grupos",
    "grupo": "Grupo L",
    "data": "2026-06-27",
    "horario": "18:00",
    "selecaoA": "Croácia",
    "selecaoB": "Gana",
    "estadio": "Estádio da Filadélfia",
    "cidade": "Filadélfia",
    "status": "Aguardando jogo",
    "placarA": null,
    "placarB": null
  },
  {
    "id": "j069",
    "numero": 69,
    "fase": "Fase de grupos",
    "grupo": "Grupo J",
    "data": "2026-06-27",
    "horario": "23:00",
    "selecaoA": "Argélia",
    "selecaoB": "Áustria",
    "estadio": "Estádio de Kansas City",
    "cidade": "Kansas City",
    "status": "Aguardando jogo",
    "placarA": null,
    "placarB": null
  },
  {
    "id": "j070",
    "numero": 70,
    "fase": "Fase de grupos",
    "grupo": "Grupo J",
    "data": "2026-06-27",
    "horario": "23:00",
    "selecaoA": "Jordânia",
    "selecaoB": "Argentina",
    "estadio": "Estádio de Dallas",
    "cidade": "Dallas",
    "status": "Aguardando jogo",
    "placarA": null,
    "placarB": null
  },
  {
    "id": "j071",
    "numero": 71,
    "fase": "Fase de grupos",
    "grupo": "Grupo K",
    "data": "2026-06-27",
    "horario": "20:30",
    "selecaoA": "Colômbia",
    "selecaoB": "Portugal",
    "estadio": "Estádio de Miami",
    "cidade": "Miami",
    "status": "Aguardando jogo",
    "placarA": null,
    "placarB": null
  },
  {
    "id": "j072",
    "numero": 72,
    "fase": "Fase de grupos",
    "grupo": "Grupo K",
    "data": "2026-06-27",
    "horario": "20:30",
    "selecaoA": "RD Congo",
    "selecaoB": "Uzbequistão",
    "estadio": "Estádio de Atlanta",
    "cidade": "Atlanta",
    "status": "Aguardando jogo",
    "placarA": null,
    "placarB": null
  },
  {
    "id": "j073",
    "numero": 73,
    "fase": "Fase eliminatória inicial",
    "grupo": "",
    "data": "2026-06-28",
    "horario": "16:00",
    "selecaoA": "2º Grupo A",
    "selecaoB": "2º Grupo B",
    "estadio": "Estádio de Los Angeles",
    "cidade": "Los Angeles",
    "status": "Aguardando classificados",
    "placarA": null,
    "placarB": null
  },
  {
    "id": "j074",
    "numero": 74,
    "fase": "Fase eliminatória inicial",
    "grupo": "",
    "data": "2026-06-29",
    "horario": "17:30",
    "selecaoA": "1º Grupo E",
    "selecaoB": "3º Grupo A/B/C/D/F",
    "estadio": "Estádio de Boston",
    "cidade": "Boston",
    "status": "Aguardando classificados",
    "placarA": null,
    "placarB": null
  },
  {
    "id": "j075",
    "numero": 75,
    "fase": "Fase eliminatória inicial",
    "grupo": "",
    "data": "2026-06-29",
    "horario": "22:00",
    "selecaoA": "1º Grupo F",
    "selecaoB": "2º Grupo C",
    "estadio": "Estádio de Monterrey",
    "cidade": "Monterrey",
    "status": "Aguardando classificados",
    "placarA": null,
    "placarB": null
  },
  {
    "id": "j076",
    "numero": 76,
    "fase": "Fase eliminatória inicial",
    "grupo": "",
    "data": "2026-06-29",
    "horario": "14:00",
    "selecaoA": "1º Grupo C",
    "selecaoB": "2º Grupo F",
    "estadio": "Estádio de Houston",
    "cidade": "Houston",
    "status": "Aguardando classificados",
    "placarA": null,
    "placarB": null
  },
  {
    "id": "j077",
    "numero": 77,
    "fase": "Fase eliminatória inicial",
    "grupo": "",
    "data": "2026-06-30",
    "horario": "18:00",
    "selecaoA": "1º Grupo I",
    "selecaoB": "3º Grupo C/D/F/G/H",
    "estadio": "Estádio de Nova York/Nova Jersey",
    "cidade": "Nova York/Nova Jersey",
    "status": "Aguardando classificados",
    "placarA": null,
    "placarB": null
  },
  {
    "id": "j078",
    "numero": 78,
    "fase": "Fase eliminatória inicial",
    "grupo": "",
    "data": "2026-06-30",
    "horario": "14:00",
    "selecaoA": "2º Grupo E",
    "selecaoB": "2º Grupo I",
    "estadio": "Estádio de Dallas",
    "cidade": "Dallas",
    "status": "Aguardando classificados",
    "placarA": null,
    "placarB": null
  },
  {
    "id": "j079",
    "numero": 79,
    "fase": "Fase eliminatória inicial",
    "grupo": "",
    "data": "2026-06-30",
    "horario": "22:00",
    "selecaoA": "1º Grupo A",
    "selecaoB": "3º Grupo C/E/F/H/I",
    "estadio": "Estádio da Cidade do México",
    "cidade": "Cidade do México",
    "status": "Aguardando classificados",
    "placarA": null,
    "placarB": null
  },
  {
    "id": "j080",
    "numero": 80,
    "fase": "Fase eliminatória inicial",
    "grupo": "",
    "data": "2026-07-01",
    "horario": "13:00",
    "selecaoA": "1º Grupo L",
    "selecaoB": "3º Grupo E/H/I/J/K",
    "estadio": "Estádio de Atlanta",
    "cidade": "Atlanta",
    "status": "Aguardando classificados",
    "placarA": null,
    "placarB": null
  },
  {
    "id": "j081",
    "numero": 81,
    "fase": "Fase eliminatória inicial",
    "grupo": "",
    "data": "2026-07-01",
    "horario": "21:00",
    "selecaoA": "1º Grupo D",
    "selecaoB": "3º Grupo B/E/F/I/J",
    "estadio": "Estádio da Baía de São Francisco",
    "cidade": "São Francisco",
    "status": "Aguardando classificados",
    "placarA": null,
    "placarB": null
  },
  {
    "id": "j082",
    "numero": 82,
    "fase": "Fase eliminatória inicial",
    "grupo": "",
    "data": "2026-07-01",
    "horario": "17:00",
    "selecaoA": "1º Grupo G",
    "selecaoB": "3º Grupo A/E/H/I/J",
    "estadio": "Estádio de Seattle",
    "cidade": "Seattle",
    "status": "Aguardando classificados",
    "placarA": null,
    "placarB": null
  },
  {
    "id": "j083",
    "numero": 83,
    "fase": "Fase eliminatória inicial",
    "grupo": "",
    "data": "2026-07-02",
    "horario": "20:00",
    "selecaoA": "2º Grupo K",
    "selecaoB": "2º Grupo L",
    "estadio": "Estádio de Toronto",
    "cidade": "Toronto",
    "status": "Aguardando classificados",
    "placarA": null,
    "placarB": null
  },
  {
    "id": "j084",
    "numero": 84,
    "fase": "Fase eliminatória inicial",
    "grupo": "",
    "data": "2026-07-02",
    "horario": "16:00",
    "selecaoA": "1º Grupo H",
    "selecaoB": "2º Grupo J",
    "estadio": "Estádio de Los Angeles",
    "cidade": "Los Angeles",
    "status": "Aguardando classificados",
    "placarA": null,
    "placarB": null
  },
  {
    "id": "j085",
    "numero": 85,
    "fase": "Fase eliminatória inicial",
    "grupo": "",
    "data": "2026-07-03",
    "horario": "00:00",
    "selecaoA": "1º Grupo B",
    "selecaoB": "3º Grupo E/F/G/I/J",
    "estadio": "BC Place",
    "cidade": "Vancouver",
    "status": "Aguardando classificados",
    "placarA": null,
    "placarB": null
  },
  {
    "id": "j086",
    "numero": 86,
    "fase": "Fase eliminatória inicial",
    "grupo": "",
    "data": "2026-07-03",
    "horario": "19:00",
    "selecaoA": "1º Grupo J",
    "selecaoB": "2º Grupo H",
    "estadio": "Estádio de Miami",
    "cidade": "Miami",
    "status": "Aguardando classificados",
    "placarA": null,
    "placarB": null
  },
  {
    "id": "j087",
    "numero": 87,
    "fase": "Fase eliminatória inicial",
    "grupo": "",
    "data": "2026-07-03",
    "horario": "22:30",
    "selecaoA": "1º Grupo K",
    "selecaoB": "3º Grupo D/E/I/J/L",
    "estadio": "Estádio de Kansas City",
    "cidade": "Kansas City",
    "status": "Aguardando classificados",
    "placarA": null,
    "placarB": null
  },
  {
    "id": "j088",
    "numero": 88,
    "fase": "Fase eliminatória inicial",
    "grupo": "",
    "data": "2026-07-03",
    "horario": "15:00",
    "selecaoA": "2º Grupo D",
    "selecaoB": "2º Grupo G",
    "estadio": "Estádio de Dallas",
    "cidade": "Dallas",
    "status": "Aguardando classificados",
    "placarA": null,
    "placarB": null
  },
  {
    "id": "j089",
    "numero": 89,
    "fase": "Oitavas de final",
    "grupo": "",
    "data": "2026-07-04",
    "horario": "18:00",
    "selecaoA": "Vencedor Jogo 74",
    "selecaoB": "Vencedor Jogo 77",
    "estadio": "Estádio da Filadélfia",
    "cidade": "Filadélfia",
    "status": "Aguardando classificados",
    "placarA": null,
    "placarB": null
  },
  {
    "id": "j090",
    "numero": 90,
    "fase": "Oitavas de final",
    "grupo": "",
    "data": "2026-07-04",
    "horario": "14:00",
    "selecaoA": "Vencedor Jogo 73",
    "selecaoB": "Vencedor Jogo 75",
    "estadio": "Estádio de Houston",
    "cidade": "Houston",
    "status": "Aguardando classificados",
    "placarA": null,
    "placarB": null
  },
  {
    "id": "j091",
    "numero": 91,
    "fase": "Oitavas de final",
    "grupo": "",
    "data": "2026-07-05",
    "horario": "17:00",
    "selecaoA": "Vencedor Jogo 76",
    "selecaoB": "Vencedor Jogo 78",
    "estadio": "Estádio de Nova York/Nova Jersey",
    "cidade": "Nova York/Nova Jersey",
    "status": "Aguardando classificados",
    "placarA": null,
    "placarB": null
  },
  {
    "id": "j092",
    "numero": 92,
    "fase": "Oitavas de final",
    "grupo": "",
    "data": "2026-07-05",
    "horario": "21:00",
    "selecaoA": "Vencedor Jogo 79",
    "selecaoB": "Vencedor Jogo 80",
    "estadio": "Estádio da Cidade do México",
    "cidade": "Cidade do México",
    "status": "Aguardando classificados",
    "placarA": null,
    "placarB": null
  },
  {
    "id": "j093",
    "numero": 93,
    "fase": "Oitavas de final",
    "grupo": "",
    "data": "2026-07-06",
    "horario": "16:00",
    "selecaoA": "Vencedor Jogo 83",
    "selecaoB": "Vencedor Jogo 84",
    "estadio": "Estádio de Dallas",
    "cidade": "Dallas",
    "status": "Aguardando classificados",
    "placarA": null,
    "placarB": null
  },
  {
    "id": "j094",
    "numero": 94,
    "fase": "Oitavas de final",
    "grupo": "",
    "data": "2026-07-06",
    "horario": "21:00",
    "selecaoA": "Vencedor Jogo 81",
    "selecaoB": "Vencedor Jogo 82",
    "estadio": "Estádio de Seattle",
    "cidade": "Seattle",
    "status": "Aguardando classificados",
    "placarA": null,
    "placarB": null
  },
  {
    "id": "j095",
    "numero": 95,
    "fase": "Oitavas de final",
    "grupo": "",
    "data": "2026-07-07",
    "horario": "13:00",
    "selecaoA": "Vencedor Jogo 86",
    "selecaoB": "Vencedor Jogo 88",
    "estadio": "Estádio de Atlanta",
    "cidade": "Atlanta",
    "status": "Aguardando classificados",
    "placarA": null,
    "placarB": null
  },
  {
    "id": "j096",
    "numero": 96,
    "fase": "Oitavas de final",
    "grupo": "",
    "data": "2026-07-07",
    "horario": "17:00",
    "selecaoA": "Vencedor Jogo 85",
    "selecaoB": "Vencedor Jogo 87",
    "estadio": "BC Place",
    "cidade": "Vancouver",
    "status": "Aguardando classificados",
    "placarA": null,
    "placarB": null
  },
  {
    "id": "j097",
    "numero": 97,
    "fase": "Quartas de final",
    "grupo": "",
    "data": "2026-07-09",
    "horario": "17:00",
    "selecaoA": "Vencedor Jogo 89",
    "selecaoB": "Vencedor Jogo 90",
    "estadio": "Estádio de Boston",
    "cidade": "Boston",
    "status": "Aguardando classificados",
    "placarA": null,
    "placarB": null
  },
  {
    "id": "j098",
    "numero": 98,
    "fase": "Quartas de final",
    "grupo": "",
    "data": "2026-07-10",
    "horario": "16:00",
    "selecaoA": "Vencedor Jogo 93",
    "selecaoB": "Vencedor Jogo 94",
    "estadio": "Estádio de Los Angeles",
    "cidade": "Los Angeles",
    "status": "Aguardando classificados",
    "placarA": null,
    "placarB": null
  },
  {
    "id": "j099",
    "numero": 99,
    "fase": "Quartas de final",
    "grupo": "",
    "data": "2026-07-11",
    "horario": "18:00",
    "selecaoA": "Vencedor Jogo 91",
    "selecaoB": "Vencedor Jogo 92",
    "estadio": "Estádio de Miami",
    "cidade": "Miami",
    "status": "Aguardando classificados",
    "placarA": null,
    "placarB": null
  },
  {
    "id": "j100",
    "numero": 100,
    "fase": "Quartas de final",
    "grupo": "",
    "data": "2026-07-11",
    "horario": "22:00",
    "selecaoA": "Vencedor Jogo 95",
    "selecaoB": "Vencedor Jogo 96",
    "estadio": "Estádio de Kansas City",
    "cidade": "Kansas City",
    "status": "Aguardando classificados",
    "placarA": null,
    "placarB": null
  },
  {
    "id": "j101",
    "numero": 101,
    "fase": "Semifinal",
    "grupo": "",
    "data": "2026-07-14",
    "horario": "16:00",
    "selecaoA": "Vencedor Jogo 97",
    "selecaoB": "Vencedor Jogo 98",
    "estadio": "Estádio de Dallas",
    "cidade": "Dallas",
    "status": "Aguardando classificados",
    "placarA": null,
    "placarB": null
  },
  {
    "id": "j102",
    "numero": 102,
    "fase": "Semifinal",
    "grupo": "",
    "data": "2026-07-15",
    "horario": "16:00",
    "selecaoA": "Vencedor Jogo 99",
    "selecaoB": "Vencedor Jogo 100",
    "estadio": "Estádio de Atlanta",
    "cidade": "Atlanta",
    "status": "Aguardando classificados",
    "placarA": null,
    "placarB": null
  },
  {
    "id": "j103",
    "numero": 103,
    "fase": "Disputa de terceiro lugar",
    "grupo": "",
    "data": "2026-07-18",
    "horario": "18:00",
    "selecaoA": "Perdedor Jogo 101",
    "selecaoB": "Perdedor Jogo 102",
    "estadio": "Estádio de Miami",
    "cidade": "Miami",
    "status": "Aguardando classificados",
    "placarA": null,
    "placarB": null
  },
  {
    "id": "j104",
    "numero": 104,
    "fase": "Final",
    "grupo": "",
    "data": "2026-07-19",
    "horario": "16:00",
    "selecaoA": "Vencedor Jogo 101",
    "selecaoB": "Vencedor Jogo 102",
    "estadio": "Estádio de Nova York/Nova Jersey",
    "cidade": "Nova York/Nova Jersey",
    "status": "Aguardando classificados",
    "placarA": null,
    "placarB": null
  }
]